<mets:mets xmlns:mets="http://www.loc.gov/METS/" xmlns:mods="http://www.loc.gov/mods/v3" xmlns:xlink="http://www.w3.org/1999/xlink">
    <mets:dmdSec ID="DMD_biejournals_3307">
        <mets:mdWrap MIMETYPE="text/xml" MDTYPE="MODS">
            <mets:xmlData>
                <mods xmlns="http://www.loc.gov/mods/v3" version="3.7" xmlns:vl="http://visuallibrary.net/vl">
                    <titleInfo lang="ger">
                        <title>Osmotische Wirkung von Kochsalz</title>
                        <subTitle>Ein Schülerexperiment zur Bestimmung der Zellsaftkonzentration bei verschiedenen Gemüsearten</subTitle>
                    </titleInfo>
                    <name type="personal">
                        <displayForm>Schumacher, Fabian</displayForm>
                        <namePart type="family">Schumacher</namePart>
                        <namePart type="given">Fabian</namePart>
                        <role>
                            <roleTerm type="code" authority="marcrelator">ctb</roleTerm>
                        </role>
                    </name>
                    <name type="personal">
                        <displayForm>Beyer-Sehlmeyer, Gabriele</displayForm>
                        <namePart type="family">Beyer-Sehlmeyer</namePart>
                        <namePart type="given">Gabriele</namePart>
                        <role>
                            <roleTerm type="code" authority="marcrelator">ctb</roleTerm>
                        </role>
                    </name>
                    <name type="personal">
                        <displayForm>Henrich, Stefanie</displayForm>
                        <namePart type="family">Henrich</namePart>
                        <namePart type="given">Stefanie</namePart>
                        <role>
                            <roleTerm type="code" authority="marcrelator">ctb</roleTerm>
                        </role>
                    </name>
                    <name type="personal">
                        <displayForm>Polte, Sabrina</displayForm>
                        <namePart type="family">Polte</namePart>
                        <namePart type="given">Sabrina</namePart>
                        <role>
                            <roleTerm type="code" authority="marcrelator">ctb</roleTerm>
                        </role>
                    </name>
                    <name type="personal">
                        <displayForm>Stockey, Andreas</displayForm>
                        <namePart type="family">Stockey</namePart>
                        <namePart type="given">Andreas</namePart>
                        <role>
                            <roleTerm type="code" authority="marcrelator">ctb</roleTerm>
                        </role>
                    </name>
                    <name type="personal">
                        <displayForm>Wilde, Matthias</displayForm>
                        <namePart type="family">Wilde</namePart>
                        <namePart type="given">Matthias</namePart>
                        <role>
                            <roleTerm type="code" authority="marcrelator">ctb</roleTerm>
                        </role>
                    </name>
                    <typeOfResource>text</typeOfResource>
                    <genre authority="dini">article</genre>
                    <originInfo>
                        <dateIssued encoding="w3cdtf" keyDate="yes">2020-02-19</dateIssued>
                    </originInfo>
                    <language>
                        <languageTerm type="code" authority="iso639-2b">ger</languageTerm>
                    </language>
                    <physicalDescription>
                        <extent unit="page">10</extent>
                    </physicalDescription>
                    <abstract lang="ger">Salze sind für Lebewesen lebenswichtig. In hohen Konzentrationen wirken sie aber u.U. toxisch. In vorhergehenden Unterrichtseinheiten haben sich die Schüler*innen bereits mit dem Aufbau und der Struktur von tierischen und pflanzlichen Zellen beschäftigt. In der vorliegenden Einheit wird den Schüler*innen die Gelegenheit gegeben, die Wirkung von Salzen auf Zellen zu verstehen. Eine Messung der Gewichtsveränderung, verursacht durch osmotische Vorgänge in den Zellen, ermöglicht die Bestimmung und den Vergleich der Zellsaft-Konzentration von Gemüsearten.</abstract>
                    <subject lang="ger">
First argument to forEach is not an array or JSON objectFirst argument to forEach is not an array or JSON objectFirst argument to forEach is not an array or JSON objectFirst argument to forEach is not an array or JSON objectFirst argument to forEach is not an array or JSON object                    </subject>
                    <subject lang="eng">
                    </subject>
                    <relatedItem type="host">
                        <titleInfo>
                            <title>PraxisForschungLehrer*innenBildung. Zeitschrift für Schul- und Professionsentwicklung.</title>
                        </titleInfo>
                        <identifier type="issn">2629-5628</identifier>
                        <part>
                            <detail type="volume">
                                <number>2</number>
                            </detail>
                            <detail type="issue">
                                <number>2</number>
                            </detail>
                            <extent unit="page">
                                <start>97</start>
                                <end>106</end>
                            </extent>
                        </part>
                    </relatedItem>
                    <identifier type="doi">10.4119/pflb-3307</identifier>
                    <accessCondition type="use and reproduction" xlink:href="https://creativecommons.org/licenses/by-sa/4.0">CC BY-SA 4.0</accessCondition>
                    <recordInfo>
                        <recordIdentifier>biejournals_3307</recordIdentifier>
                    </recordInfo>
                    <extension>
                        <vl:doctype>oaArticle</vl:doctype>
                    </extension>
                </mods>
            </mets:xmlData>
        </mets:mdWrap>
    </mets:dmdSec>
    <mets:fileSec>
        <mets:fileGrp USE="pdf upload">
            <mets:file MIMETYPE="application/pdf" ID="FILE0_biejournals_3307">
                <mets:FLocat xlink:href="https://www.pflb-journal.de/index.php/pflb/article/download/3307/3463" LOCTYPE="URL"/>
            </mets:file>
        </mets:fileGrp>
        <mets:fileGrp USE="generic file">
            <mets:file MIMETYPE="application/pdf" ID="FILE1_biejournals_3307">
                <mets:FLocat xlink:href="https://www.pflb-journal.de/index.php/pflb/article/download/3307/3464" LOCTYPE="URL"/>
            </mets:file>
        </mets:fileGrp>
    </mets:fileSec>
    <mets:structMap TYPE="LOGICAL">
        <mets:div TYPE="document" ID="biejournals_3307" DMDID="DMD_biejournals_3307">
            <mets:fptr FILEID="FILE0_biejournals_3307"/>
            <mets:div TYPE="part" ID="PART1_biejournals_3307" LABEL="">
                <mets:fptr FILEID="FILE1_biejournals_3307"/>
            </mets:div>
        </mets:div>
    </mets:structMap>
</mets:mets>
