<mets:mets xmlns:mets="http://www.loc.gov/METS/" xmlns:mods="http://www.loc.gov/mods/v3" xmlns:xlink="http://www.w3.org/1999/xlink">
    <mets:dmdSec ID="DMD_biejournals_218">
        <mets:mdWrap MIMETYPE="text/xml" MDTYPE="MODS">
            <mets:xmlData>
                <mods xmlns="http://www.loc.gov/mods/v3" version="3.7" xmlns:vl="http://visuallibrary.net/vl">
                    <titleInfo lang="ger">
                        <title>Alexandra Jürgens (2017). Determinanten des Studienerfolgs. Nichttraditionell Studierende in ingenieurwissenschaftlichen Studiengängen. Bielefeld</title>
                        <subTitle>W. Bertelsmann Verlag.</subTitle>
                    </titleInfo>
                    <name type="personal">
                        <displayForm>Klenk, Johannes</displayForm>
                        <namePart type="family">Klenk</namePart>
                        <namePart type="given">Johannes</namePart>
                        <role>
                            <roleTerm type="code" authority="marcrelator">ctb</roleTerm>
                        </role>
                    </name>
                    <typeOfResource>text</typeOfResource>
                    <genre authority="dini">article</genre>
                    <originInfo>
                        <dateIssued encoding="w3cdtf" keyDate="yes">2017-12-17</dateIssued>
                    </originInfo>
                    <physicalDescription>
                        <extent unit="page">1</extent>
                    </physicalDescription>
                    <recordInfo>
                        <recordIdentifier>biejournals_218</recordIdentifier>
                    </recordInfo>
                </mods>
            </mets:xmlData>
        </mets:mdWrap>
    </mets:dmdSec>
    <mets:fileSec>
        <mets:fileGrp USE="pdf upload">
            <mets:file MIMETYPE="application/pdf" ID="FILE0_biejournals_218">
                <mets:FLocat xlink:href="https://www.hochschule-und-weiterbildung.net/index.php/zhwb/article/download/218/220" LOCTYPE="URL"/>
            </mets:file>
        </mets:fileGrp>
    </mets:fileSec>
    <mets:structMap TYPE="LOGICAL">
        <mets:div TYPE="document" ID="biejournals_218" DMDID="DMD_biejournals_218">
            <mets:fptr FILEID="FILE0_biejournals_218"/>
        </mets:div>
    </mets:structMap>
</mets:mets>
