<?xml version="1.0" encoding="utf-8"?>
<Record>
  <header status="">
    <identifier>oai:biejournals.de:article/4575</identifier>
    <datestamp>2021-08-09T07:16:40Z</datestamp>
    <setSpec>biuz:HA</setSpec>
  </header>
  <metadata>
    <oai_dc:dc xmlns:oai_dc="http://www.openarchives.org/OAI/2.0/oai_dc/" xmlns:dc="http://purl.org/dc/elements/1.1/" xmlns:xsi="http://www.w3.org/2001/XMLSchema-instance" xsi:schemaLocation="http://www.openarchives.org/OAI/2.0/oai_dc/ http://www.openarchives.org/OAI/2.0/oai_dc.xsd">
      <dc:title xml:lang="de-DE">Maritime Funktionsmorphologie: Biologisch-technische Analogien rund um das Meer</dc:title>
      <dc:title xml:lang="en-US">Maritime functional morphology:  </dc:title>
      <dc:creator>Hasenpusch, Wolfgang</dc:creator>
      <dc:subject xml:lang="de-DE">Maritime Funktionsmorphologie</dc:subject>
      <dc:subject xml:lang="de-DE">Bionik</dc:subject>
      <dc:subject xml:lang="de-DE">Haifischzähne</dc:subject>
      <dc:subject xml:lang="de-DE">Seeigelstacheln</dc:subject>
      <dc:subject xml:lang="de-DE">Seeigelzähne</dc:subject>
      <dc:subject xml:lang="de-DE">Sepienschulp</dc:subject>
      <dc:description xml:lang="de-DE">Die Meere mit ihren großen Oberflächen und Tiefen haben ihren Bewohnern im Laufe der Evolution zu einer erstaunlichen Fülle spezifischer Funktionsmorphologien verholfen. Das lässt sich an den Beispielen der harten Haifischzähne, den Wasserwiderstand mindernden Seeigelstacheln, kalottenförmigen Papageifischzähnen, den Angst einflößenden giftigen Seeschlangen und den extrem tief tauchenden Walen eindrucksvoll aufzeigen und kann zu entsprechenden technischen Anwendungen anregen.</dc:description>
      <dc:description xml:lang="en-US">During the course of evolution, conditions in the wide and deep oceans have led to an amazing diversity of functional morphologies in living organisms. That can be impressively demonstrated with some examples: the hard teeth of sharks, the spines of sea urchins which so efficiently reduce water resistance, the tough teeth of Parrot fish with their dome-shaped caps, highly toxic frightening sea snakes and extremely deep diving whales – all of these animals displaying structures and processes that may trigger technical  applications.</dc:description>
      <dc:publisher xml:lang="de-DE">VBiO - Verband Biologie, Biowissenschaften &amp; Biomedizin in Deutschland</dc:publisher>
      <dc:date>2021-08-09</dc:date>
      <dc:type>info:eu-repo/semantics/article</dc:type>
      <dc:type>info:eu-repo/semantics/publishedVersion</dc:type>
      <dc:format>application/pdf</dc:format>
      <dc:identifier>https://www.biuz.de/index.php/biuz/article/view/4575</dc:identifier>
      <dc:identifier>10.11576/biuz-4575</dc:identifier>
      <dc:source xml:lang="de-DE">Biologie in unserer Zeit; Bd. 51 Nr. 3 (2021): Edmonds Urzeit; 281-287</dc:source>
      <dc:source xml:lang="en-US">Biologie in unserer Zeit; Vol. 51 No. 3 (2021): Edmonds Urzeit; 281-287</dc:source>
      <dc:source>1521-415X</dc:source>
      <dc:source>0045-205X</dc:source>
      <dc:language>deu</dc:language>
      <dc:relation>https://www.biuz.de/index.php/biuz/article/view/4575/4384</dc:relation>
      <dc:rights xml:lang="de-DE">Copyright (c) 2021 Wolfgang Hasenpusch</dc:rights>
      <dc:rights xml:lang="de-DE">https://creativecommons.org/licenses/by-sa/4.0</dc:rights>
    </oai_dc:dc>
  </metadata>
  <about/>
</Record>
